{
  "id": "group:Malta",
  "primary_id": "group:Malta",
  "type": "group",
  "group_type": "other",
  "localizations": {
    "eng": {
      "preferred_label": "Malta Islanders",
      "descriptions": [
        {
          "source": "acai",
          "gloss": "Malta Islanders",
          "description": "People who live on the island of Malta."
        }
      ]
    }
  },
  "only_mentioned_in_apocrypha": false,
  "non_biblical": false,
  "key_references": [
    "44028004",
    "44028004"
  ],
  "references": [
    "44028004",
    "44028004"
  ],
  "subject_referents": {
    "SBLGNT": [
      [
        "n44028004005"
      ],
      [
        "n44028004015"
      ]
    ]
  },
  "speeches": {
    "SBLGNT": [
      {
        "delivery": "suspicious",
        "quote_type": "Normal",
        "words": [
          "n44028004016",
          "n44028004017",
          "n44028004018",
          "n44028004019",
          "n44028004020",
          "n44028004021",
          "n44028004022",
          "n44028004023",
          "n44028004024",
          "n44028004025",
          "n44028004026",
          "n44028004027",
          "n44028004028",
          "n44028004029",
          "n44028004030",
          "n44028004031"
        ]
      }
    ]
  }
}