{
  "id": "keyterm:Command",
  "primary_id": "keyterm:Command",
  "type": "keyterm",
  "keyterm_type": "attributes",
  "ubsdgnt": [
    "33.329",
    "33.331",
    "33.419",
    "33.69"
  ],
  "localizations": {
    "eng": {
      "preferred_label": "To Command (Give Orders)",
      "descriptions": [
        {
          "source": "acai",
          "description": "To give clear orders that show authority or official power."
        }
      ]
    },
    "spa": {
      "preferred_label": "mandar"
    },
    "fra": {
      "preferred_label": "prescrire"
    },
    "ind": {
      "preferred_label": "memerintahkan"
    },
    "por-Br": {
      "preferred_label": "comandar"
    }
  },
  "referred_to_as": [
    "keyterm:Command.2",
    "keyterm:Command.3",
    "keyterm:Rebuke"
  ],
  "only_mentioned_in_apocrypha": false,
  "non_biblical": false,
  "lemmas": {
    "el": [
      "ἐντέλλομαι",
      "ἐπιτιμάω",
      "εἶπον"
    ]
  },
  "key_references": [
    "40008026",
    "41004039",
    "42004035",
    "43015014"
  ],
  "references": [
    "40004006",
    "40017009",
    "40019007",
    "40028020",
    "41010003",
    "41013034",
    "42004010",
    "43008005",
    "43014031",
    "43015014",
    "43015017",
    "44001002",
    "44013047",
    "58009020",
    "58011022",
    "40008026",
    "40012016",
    "40016022",
    "40017018",
    "40019013",
    "40020031",
    "41001025",
    "41003012",
    "41004039",
    "41008030",
    "41008032",
    "41008033",
    "41009025",
    "41010013",
    "41010048",
    "42004035",
    "42004039",
    "42004041",
    "42008024",
    "42009021",
    "42009042",
    "42009055",
    "42017003",
    "42018015",
    "42018039",
    "42019039",
    "42023040",
    "55004002",
    "65001009",
    "40004003",
    "40008008",
    "40010027",
    "40020021",
    "40021005",
    "40022004",
    "41016007",
    "42004003",
    "42007007",
    "42010040",
    "42012013",
    "51004017",
    "66022017"
  ],
  "explicit_instances": {
    "SBLGNT": [
      [
        "n40004006018"
      ],
      [
        "n40017009007"
      ],
      [
        "n40019007006"
      ],
      [
        "n40028020006"
      ],
      [
        "n41010003008"
      ],
      [
        "n41013034022"
      ],
      [
        "n42004010007"
      ],
      [
        "n43008005007"
      ],
      [
        "n43014031012"
      ],
      [
        "n43015014009"
      ],
      [
        "n43015017002"
      ],
      [
        "n44001002004"
      ],
      [
        "n44013047003"
      ],
      [
        "n58009020008"
      ],
      [
        "n58011022016"
      ],
      [
        "n40012016002"
      ],
      [
        "n40017018002"
      ],
      [
        "n41003012003"
      ],
      [
        "n41004039003"
      ],
      [
        "n41008030002"
      ],
      [
        "n41009025008"
      ],
      [
        "n42004035002"
      ],
      [
        "n42004039005"
      ],
      [
        "n42004041018"
      ],
      [
        "n42008024012"
      ],
      [
        "n42009021003"
      ],
      [
        "n42009042011"
      ],
      [
        "n40008026010"
      ],
      [
        "n40016022007"
      ],
      [
        "n40019013015"
      ],
      [
        "n40020031004"
      ],
      [
        "n41001025002"
      ],
      [
        "n41008032012"
      ],
      [
        "n41008033009"
      ],
      [
        "n41010013011"
      ],
      [
        "n41010048002"
      ],
      [
        "n42009055003"
      ],
      [
        "n42017003008"
      ],
      [
        "n42018015014"
      ],
      [
        "n42018039004"
      ],
      [
        "n42019039012"
      ],
      [
        "n42023040005"
      ],
      [
        "n55004002008"
      ],
      [
        "n65001009022"
      ],
      [
        "n40004003012"
      ],
      [
        "n40008008018"
      ],
      [
        "n40010027007"
      ],
      [
        "n40020021009"
      ],
      [
        "n40021005001"
      ],
      [
        "n40022004006"
      ],
      [
        "n41016007003"
      ],
      [
        "n42004003011"
      ],
      [
        "n42007007009"
      ],
      [
        "n42010040023"
      ],
      [
        "n42012013009"
      ],
      [
        "n51004017002"
      ],
      [
        "n66022017012"
      ],
      [
        "n40008026010"
      ],
      [
        "n40016022007"
      ],
      [
        "n40019013015"
      ],
      [
        "n40020031004"
      ],
      [
        "n41001025002"
      ],
      [
        "n41008032012"
      ],
      [
        "n41008033009"
      ],
      [
        "n41010013011"
      ],
      [
        "n41010048002"
      ],
      [
        "n42009055003"
      ],
      [
        "n42017003008"
      ],
      [
        "n42018015014"
      ],
      [
        "n42018039004"
      ],
      [
        "n42019039012"
      ],
      [
        "n42023040005"
      ],
      [
        "n55004002008"
      ],
      [
        "n65001009022"
      ]
    ]
  },
  "subject_referents": {
    "SBLGNT": [
      [
        "n40004006012"
      ],
      [
        "n42004010001"
      ]
    ]
  }
}