{
  "id": "realia:Shovel",
  "primary_id": "realia:Shovel",
  "alternate_sources": {
    "ubsdbh": [
      "002977001001000",
      "003917001001000"
    ],
    "ubsrealia": [
      "realia:4.4.5"
    ]
  },
  "type": "realia",
  "realia_type": "other",
  "ubsdbh": [
    "002977001001000",
    "003917001001000"
  ],
  "localizations": {
    "eng": {
      "preferred_label": "Shovel",
      "alternate_labels": [
        "Scraper",
        "Firepan"
      ],
      "descriptions": [
        {
          "source": "acai",
          "gloss": "Shovel",
          "article": "realia:Shovel",
          "description": "A tool with a broad, curved blade used to remove refuse from the altar."
        }
      ]
    }
  },
  "only_mentioned_in_apocrypha": false,
  "non_biblical": false,
  "lemmas": {
    "he": [
      "יָע",
      "מַחְתָּה"
    ]
  },
  "key_references": [
    "02027003",
    "04004014",
    "12025014"
  ],
  "references": [
    "02025038",
    "02027003",
    "02037023",
    "02038003",
    "03010001",
    "03016012",
    "04004009",
    "04004014",
    "04016006",
    "04016017",
    "04016018",
    "04017002",
    "04017003",
    "04017004",
    "04017011",
    "11007040",
    "11007045",
    "11007050",
    "12025014",
    "12025015",
    "14004011",
    "14004016",
    "14004022",
    "24052018",
    "24052019"
  ],
  "explicit_instances": {
    "wlc": [
      [
        "o020270030042",
        "o020270030043"
      ],
      [
        "o020380030092"
      ],
      [
        "o040040140152"
      ],
      [
        "o110070400062"
      ],
      [
        "o110070450042"
      ],
      [
        "o120250140042"
      ],
      [
        "o140040110062"
      ],
      [
        "o140040160042"
      ],
      [
        "o240520180042"
      ],
      [
        "o020250380022",
        "o020250380023"
      ],
      [
        "o020270030072",
        "o020270030073"
      ],
      [
        "o020370230062",
        "o020370230063"
      ],
      [
        "o020380030152"
      ],
      [
        "o030100010071",
        "o030100010072"
      ],
      [
        "o030160120032"
      ],
      [
        "o040040090131",
        "o040040090132"
      ],
      [
        "o040040140112"
      ],
      [
        "o040160060051"
      ],
      [
        "o040160170031",
        "o040160170032"
      ],
      [
        "o040160170111",
        "o040160170112"
      ],
      [
        "o040160170141"
      ],
      [
        "o040160170181",
        "o040160170182"
      ],
      [
        "o040160180031",
        "o040160180032"
      ],
      [
        "o040170020092"
      ],
      [
        "o040170030021"
      ],
      [
        "o040170040051"
      ],
      [
        "o040170110072"
      ],
      [
        "o110070500053"
      ],
      [
        "o120250150022"
      ],
      [
        "o140040220043"
      ],
      [
        "o240520190042"
      ]
    ]
  },
  "pronominal_referents": {
    "wlc": [
      [
        "o140040160092"
      ],
      [
        "o140040170032"
      ],
      [
        "o140040180052"
      ],
      [
        "o030100010092"
      ],
      [
        "o030100010122"
      ],
      [
        "o040160070022"
      ],
      [
        "o040160070052"
      ],
      [
        "o040160170052"
      ],
      [
        "o040160180052"
      ],
      [
        "o040160180082"
      ],
      [
        "o040170030072"
      ],
      [
        "o040170030132"
      ],
      [
        "o040170040103"
      ],
      [
        "o040170110092"
      ]
    ]
  },
  "subject_referents": {
    "wlc": [
      [
        "o040170020171"
      ],
      [
        "o040170030162"
      ],
      [
        "o040170030172"
      ]
    ]
  }
}