{
  "id": "person:Diotrephes",
  "primary_id": "person:Diotrephes",
  "alternate_sources": {
    "aquifer": [
      "4855|Diotrephes|TyndaleBibleDictionary"
    ],
    "ubsdgnt": [
      "93.99"
    ],
    "tipnr": [
      "Diotrephes@3Jn.1.9"
    ],
    "vizbible": [
      "recRd8VDsVN2BRjwo"
    ]
  },
  "type": "person",
  "gender": "male",
  "ubsdgnt": [
    "93.99"
  ],
  "localizations": {
    "eng": {
      "preferred_label": "Diotrephes",
      "descriptions": [
        {
          "source": "acai",
          "gloss": "Diotrephes",
          "article": "person:Diotrephes",
          "description": "Diotrephes was a New Testament Christian criticized for his behavior, mentioned in 3 John 1:9."
        }
      ]
    }
  },
  "only_mentioned_in_apocrypha": false,
  "non_biblical": false,
  "lemmas": {
    "el": [
      "Διοτρέφης"
    ]
  },
  "key_references": [
    "64001009"
  ],
  "references": [
    "64001009"
  ],
  "explicit_instances": {
    "SBLGNT": [
      [
        "n64001009009"
      ]
    ]
  },
  "subject_referents": {
    "SBLGNT": [
      [
        "n64001009007"
      ]
    ]
  }
}