{
  "id": "person:Gideon",
  "primary_id": "person:Gideon",
  "alternate_sources": {
    "aquifer": [
      "5458|Gideon|TyndaleBibleDictionary",
      "26638|Gideon|UWTranslationWords",
      "132383|Gideon|BiblicaStudyNotesKeyTerms"
    ],
    "tipnr": [
      "Gideon@Jdg.6.11-Heb",
      "Jerubbaal|Gideon@Jdg.6.11-Heb",
      "Jerubbesheth|Gideon@Jdg.6.11-Heb"
    ],
    "vizbible": [
      "recjU9TzJTjllYnUJ"
    ]
  },
  "type": "person",
  "gender": "male",
  "father": "person:Joash",
  "offspring": [
    "person:Jether.2",
    "person:Abimelech.2",
    "person:Jotham"
  ],
  "roles": [
    "Judge"
  ],
  "localizations": {
    "eng": {
      "preferred_label": "Gideon",
      "alternate_labels": [
        "Jerubbaal",
        "Gedeon",
        "Jerubbesheth"
      ],
      "descriptions": [
        {
          "source": "acai",
          "gloss": "Gideon",
          "article": "person:Gideon",
          "description": "A son of Joash the Abiezrite from the tribe of Manasseh, who served as a judge of Israel. He was father of Jether, Abimelech, and Jotham."
        }
      ]
    },
    "arb": {
      "preferred_label": "جِدْعونَ"
    },
    "cmn": {
      "preferred_label": "基甸"
    },
    "fra": {
      "preferred_label": "Gédéon"
    },
    "hau": {
      "preferred_label": "Gideyon"
    },
    "hin": {
      "preferred_label": "गिदोन"
    },
    "ind": {
      "preferred_label": "Gideon"
    },
    "por": {
      "preferred_label": "Gideão"
    },
    "rus": {
      "preferred_label": "Гедеон"
    },
    "spa": {
      "preferred_label": "Gedeón"
    },
    "swh": {
      "preferred_label": "Gideoni"
    },
    "tpi": {
      "preferred_label": "Gideon"
    }
  },
  "referred_to_as": [
    "person:Jerubbaal",
    "person:Jerubbesheth"
  ],
  "only_mentioned_in_apocrypha": false,
  "non_biblical": false,
  "key_references": [
    "07006011",
    "07006032",
    "07008031",
    "07009005",
    "58011032",
    "07009020"
  ],
  "references": [
    "07006011",
    "07006013",
    "07006019",
    "07006022",
    "07006024",
    "07006027",
    "07006029",
    "07006032",
    "07006034",
    "07006036",
    "07006039",
    "07007001",
    "07007002",
    "07007004",
    "07007005",
    "07007007",
    "07007013",
    "07007014",
    "07007015",
    "07007018",
    "07007019",
    "07007020",
    "07007024",
    "07007025",
    "07008004",
    "07008007",
    "07008011",
    "07008013",
    "07008021",
    "07008022",
    "07008023",
    "07008024",
    "07008027",
    "07008028",
    "07008029",
    "07008030",
    "07008032",
    "07008033",
    "07008035",
    "07009001",
    "07009002",
    "07009005",
    "07009016",
    "07009019",
    "07009024",
    "07009028",
    "07009057",
    "09012011",
    "10011021",
    "58011032"
  ],
  "explicit_instances": {
    "wlc": [
      [
        "o070060110132"
      ],
      [
        "o070060130031"
      ],
      [
        "o070060190012"
      ],
      [
        "o070060220021"
      ],
      [
        "o070060220081"
      ],
      [
        "o070060240031"
      ],
      [
        "o070060270021"
      ],
      [
        "o070060290121"
      ],
      [
        "o070060320051"
      ],
      [
        "o070060340051"
      ],
      [
        "o070060360021"
      ],
      [
        "o070060390021"
      ],
      [
        "o070070010021"
      ],
      [
        "o070070010041"
      ],
      [
        "o070070020041"
      ],
      [
        "o070070040041"
      ],
      [
        "o070070050091"
      ],
      [
        "o070070070041"
      ],
      [
        "o070070130021"
      ],
      [
        "o070070140091"
      ],
      [
        "o070070150031"
      ],
      [
        "o070070180163"
      ],
      [
        "o070070190021"
      ],
      [
        "o070070200183"
      ],
      [
        "o070070240031"
      ],
      [
        "o070070250271"
      ],
      [
        "o070080040021"
      ],
      [
        "o070080070021"
      ],
      [
        "o070080110021"
      ],
      [
        "o070080130021"
      ],
      [
        "o070080210121"
      ],
      [
        "o070080220051"
      ],
      [
        "o070080230031"
      ],
      [
        "o070080240031"
      ],
      [
        "o070080270031"
      ],
      [
        "o070080270152"
      ],
      [
        "o070080280151"
      ],
      [
        "o070080290021"
      ],
      [
        "o070080300013"
      ],
      [
        "o070080320021"
      ],
      [
        "o070080330041"
      ],
      [
        "o070080350061",
        "o070080350071"
      ],
      [
        "o070090010041"
      ],
      [
        "o070090020161"
      ],
      [
        "o070090050091"
      ],
      [
        "o070090050181"
      ],
      [
        "o070090160131"
      ],
      [
        "o070090190061"
      ],
      [
        "o070090240051"
      ],
      [
        "o070090280131"
      ],
      [
        "o070090570141"
      ],
      [
        "o090120110041"
      ],
      [
        "o100110210061"
      ]
    ],
    "SBLGNT": [
      [
        "n58011032012"
      ]
    ]
  },
  "pronominal_referents": {
    "wlc": [
      [
        "o070060130041"
      ],
      [
        "o070060150031"
      ],
      [
        "o070060150132"
      ],
      [
        "o070060370021"
      ],
      [
        "o070070010031"
      ],
      [
        "o070070100031"
      ],
      [
        "o070070100061"
      ],
      [
        "o070070110101"
      ],
      [
        "o070070170081"
      ],
      [
        "o070070180031"
      ],
      [
        "o070080040051"
      ],
      [
        "o070080050142"
      ],
      [
        "o070080210051"
      ],
      [
        "o070080220091"
      ],
      [
        "o070080230061"
      ]
    ],
    "SBLGNT": [
      [
        "n58011033001"
      ],
      [
        "n58011039002"
      ]
    ]
  },
  "subject_referents": {
    "wlc": [
      [
        "o070060140051"
      ],
      [
        "o070060140082"
      ],
      [
        "o070060150012"
      ],
      [
        "o070060150061"
      ],
      [
        "o070060160072"
      ],
      [
        "o070060170012"
      ],
      [
        "o070060170051"
      ],
      [
        "o070060180082"
      ],
      [
        "o070060180112"
      ],
      [
        "o070060190032"
      ],
      [
        "o070060190101"
      ],
      [
        "o070060190131"
      ],
      [
        "o070060190152"
      ],
      [
        "o070060190202"
      ],
      [
        "o070060200051"
      ],
      [
        "o070060200102"
      ],
      [
        "o070060200161"
      ],
      [
        "o070060200172"
      ],
      [
        "o070060240062"
      ],
      [
        "o070060250071"
      ],
      [
        "o070060250172"
      ],
      [
        "o070060250271"
      ],
      [
        "o070060260012"
      ],
      [
        "o070060260102"
      ],
      [
        "o070060260142"
      ],
      [
        "o070060260191"
      ],
      [
        "o070060270062"
      ],
      [
        "o070060270131"
      ],
      [
        "o070060270202"
      ],
      [
        "o070060270222"
      ],
      [
        "o070060320111"
      ],
      [
        "o070060340062"
      ],
      [
        "o070060350021"
      ],
      [
        "o070060350101"
      ],
      [
        "o070060370182"
      ],
      [
        "o070060380032"
      ],
      [
        "o070060380052"
      ],
      [
        "o070060380082"
      ],
      [
        "o070060390092"
      ],
      [
        "o070060390121"
      ],
      [
        "o070070010092"
      ],
      [
        "o070070030021"
      ],
      [
        "o070070030062"
      ],
      [
        "o070070040081"
      ],
      [
        "o070070050012"
      ],
      [
        "o070070080121"
      ],
      [
        "o070070080181"
      ],
      [
        "o070070090071",
        "o070070090081"
      ],
      [
        "o070070100042"
      ],
      [
        "o070070110012"
      ],
      [
        "o070070110072"
      ],
      [
        "o070070150092"
      ],
      [
        "o070070150102"
      ],
      [
        "o070070150142"
      ],
      [
        "o070070160012"
      ],
      [
        "o070070160082"
      ],
      [
        "o070070170012"
      ],
      [
        "o070070170141"
      ],
      [
        "o070070190172"
      ],
      [
        "o070070190192"
      ],
      [
        "o070070240072"
      ],
      [
        "o070080040122"
      ],
      [
        "o070080050012"
      ],
      [
        "o070080070112"
      ],
      [
        "o070080080012"
      ],
      [
        "o070080080042"
      ],
      [
        "o070080090012"
      ],
      [
        "o070080090052"
      ],
      [
        "o070080090081"
      ],
      [
        "o070080110092"
      ],
      [
        "o070080120042"
      ],
      [
        "o070080120062"
      ],
      [
        "o070080120171"
      ],
      [
        "o070080140012"
      ],
      [
        "o070080140052"
      ],
      [
        "o070080150012"
      ],
      [
        "o070080150052"
      ],
      [
        "o070080160012"
      ],
      [
        "o070080160102"
      ],
      [
        "o070080170041"
      ],
      [
        "o070080170052"
      ],
      [
        "o070080180012"
      ],
      [
        "o070080190012"
      ],
      [
        "o070080190121"
      ],
      [
        "o070080200012"
      ],
      [
        "o070080210062"
      ],
      [
        "o070080210132"
      ],
      [
        "o070080210182"
      ],
      [
        "o070080220161"
      ],
      [
        "o070080240041"
      ],
      [
        "o070080260061"
      ],
      [
        "o070080270052"
      ],
      [
        "o070080290052"
      ],
      [
        "o070080310092"
      ],
      [
        "o070080320072"
      ],
      [
        "o070080350111"
      ]
    ],
    "SBLGNT": [
      [
        "n58011033006"
      ],
      [
        "n58011033008"
      ],
      [
        "n58011033010"
      ],
      [
        "n58011034001"
      ],
      [
        "n58011034004"
      ],
      [
        "n58011034007"
      ],
      [
        "n58011034010"
      ],
      [
        "n58011034015"
      ],
      [
        "n58011039003"
      ],
      [
        "n58011040012"
      ]
    ]
  },
  "speeches": {
    "wlc": [
      {
        "quote_type": "Normal",
        "words": [
          "o070060130041",
          "o070060130051",
          "o070060130052",
          "o070060130061",
          "o070060130062",
          "o070060130071",
          "o070060130081",
          "o070060130082",
          "o070060130091",
          "o070060130092",
          "o070060130093",
          "o070060130101",
          "o070060130102",
          "o070060130111",
          "o070060130121",
          "o070060130131",
          "o070060130132",
          "o070060130141",
          "o070060130151",
          "o070060130152",
          "o070060130161",
          "o070060130171",
          "o070060130181",
          "o070060130182",
          "o070060130191",
          "o070060130192",
          "o070060130201",
          "o070060130202",
          "o070060130211",
          "o070060130212",
          "o070060130221",
          "o070060130222",
          "o070060130231",
          "o070060130232",
          "o070060130241",
          "o070060130251",
          "o070060130252",
          "o070060130261",
          "o070060130262",
          "o070060130271",
          "o070060130281",
          "o070060130282",
          "o070060130283",
          "o070060130291",
          "o070060130292",
          "o070060130301"
        ]
      },
      {
        "quote_type": "Normal",
        "words": [
          "o070060150031",
          "o070060150041",
          "o070060150042",
          "o070060150051",
          "o070060150052",
          "o070060150061",
          "o070060150071",
          "o070060150081",
          "o070060150091",
          "o070060150101",
          "o070060150102",
          "o070060150111",
          "o070060150112",
          "o070060150121",
          "o070060150122",
          "o070060150131",
          "o070060150132",
          "o070060150141",
          "o070060150142",
          "o070060150151",
          "o070060150152",
          "o070060150161",
          "o070060150162"
        ]
      },
      {
        "quote_type": "Normal",
        "words": [
          "o070060170031",
          "o070060170041",
          "o070060170051",
          "o070060170061",
          "o070060170071",
          "o070060170072",
          "o070060170073",
          "o070060170081",
          "o070060170082",
          "o070060170091",
          "o070060170092",
          "o070060170101",
          "o070060170111",
          "o070060170112",
          "o070060170121",
          "o070060170131",
          "o070060170132"
        ]
      },
      {
        "quote_type": "Normal",
        "words": [
          "o070060180141",
          "o070060180151",
          "o070060180161",
          "o070060180171",
          "o070060180172"
        ]
      },
      {
        "quote_type": "Normal",
        "words": [
          "o070060220101",
          "o070060220102",
          "o070060220111",
          "o070060220121",
          "o070060220131",
          "o070060220141",
          "o070060220151",
          "o070060220161",
          "o070060220171",
          "o070060220181",
          "o070060220191",
          "o070060220201"
        ]
      },
      {
        "quote_type": "Normal",
        "words": [
          "o070060360051",
          "o070060360061",
          "o070060360062",
          "o070060360071",
          "o070060360081",
          "o070060360082",
          "o070060360083",
          "o070060360091",
          "o070060360101",
          "o070060360111",
          "o070060360112",
          "o070060360121",
          "o070060370011",
          "o070060370021",
          "o070060370031",
          "o070060370041",
          "o070060370051",
          "o070060370061",
          "o070060370062",
          "o070060370071",
          "o070060370071ה",
          "o070060370072",
          "o070060370081",
          "o070060370091",
          "o070060370101",
          "o070060370111",
          "o070060370121",
          "o070060370122",
          "o070060370131",
          "o070060370132",
          "o070060370133",
          "o070060370141",
          "o070060370142",
          "o070060370151",
          "o070060370161",
          "o070060370162",
          "o070060370171",
          "o070060370181",
          "o070060370182",
          "o070060370191",
          "o070060370201",
          "o070060370211",
          "o070060370212",
          "o070060370213",
          "o070060370221",
          "o070060370231",
          "o070060370241",
          "o070060370242",
          "o070060370251"
        ]
      },
      {
        "quote_type": "Normal",
        "words": [
          "o070060390051",
          "o070060390061",
          "o070060390071",
          "o070060390072",
          "o070060390081",
          "o070060390082",
          "o070060390091",
          "o070060390092",
          "o070060390101",
          "o070060390111",
          "o070060390112",
          "o070060390121",
          "o070060390131",
          "o070060390141",
          "o070060390151",
          "o070060390152",
          "o070060390161",
          "o070060390161ה",
          "o070060390162",
          "o070060390171",
          "o070060390181",
          "o070060390191",
          "o070060390201",
          "o070060390211",
          "o070060390212",
          "o070060390221",
          "o070060390222",
          "o070060390223",
          "o070060390231",
          "o070060390232",
          "o070060390241",
          "o070060390251",
          "o070060390252",
          "o070060390261",
          "o070060390271"
        ]
      },
      {
        "quote_type": "Normal",
        "words": [
          "o070070150151",
          "o070070150161",
          "o070070150171",
          "o070070150181",
          "o070070150191",
          "o070070150192",
          "o070070150193",
          "o070070150201",
          "o070070150211",
          "o070070150221"
        ]
      },
      {
        "quote_type": "Normal",
        "words": [
          "o070070170032",
          "o070070170041",
          "o070070170051",
          "o070070170052",
          "o070070170061",
          "o070070170071",
          "o070070170072",
          "o070070170081",
          "o070070170091",
          "o070070170101",
          "o070070170102",
          "o070070170111",
          "o070070170112",
          "o070070170121",
          "o070070170122",
          "o070070170131",
          "o070070170132",
          "o070070170141",
          "o070070170151",
          "o070070170161",
          "o070070170162",
          "o070070180011",
          "o070070180012",
          "o070070180021",
          "o070070180021ה",
          "o070070180022",
          "o070070180031",
          "o070070180041",
          "o070070180042",
          "o070070180051",
          "o070070180061",
          "o070070180062",
          "o070070180071",
          "o070070180072",
          "o070070180081",
          "o070070180081ה",
          "o070070180082",
          "o070070180091",
          "o070070180101",
          "o070070180111",
          "o070070180121",
          "o070070180131",
          "o070070180132",
          "o070070180141",
          "o070070180142",
          "o070070180151",
          "o070070180152",
          "o070070180161",
          "o070070180162",
          "o070070180163"
        ]
      },
      {
        "quote_type": "Normal",
        "words": [
          "o070070240081",
          "o070070240091",
          "o070070240092",
          "o070070240101",
          "o070070240111",
          "o070070240112",
          "o070070240121",
          "o070070240122",
          "o070070240131",
          "o070070240141",
          "o070070240142",
          "o070070240151",
          "o070070240161",
          "o070070240171",
          "o070070240181",
          "o070070240182"
        ]
      },
      {
        "quote_type": "Normal",
        "words": [
          "o070080020031",
          "o070080020041",
          "o070080020051",
          "o070080020061",
          "o070080020062",
          "o070080020071",
          "o070080020072",
          "o070080020081",
          "o070080020091",
          "o070080020101",
          "o070080020111",
          "o070080020112",
          "o070080020121",
          "o070080030011",
          "o070080030012",
          "o070080030013",
          "o070080030021",
          "o070080030031",
          "o070080030041",
          "o070080030051",
          "o070080030061",
          "o070080030071",
          "o070080030081",
          "o070080030091",
          "o070080030092",
          "o070080030101",
          "o070080030111",
          "o070080030112",
          "o070080030121",
          "o070080030131",
          "o070080030141",
          "o070080030142"
        ]
      },
      {
        "quote_type": "Normal",
        "words": [
          "o070080050041",
          "o070080050051",
          "o070080050061",
          "o070080050071",
          "o070080050081",
          "o070080050081ה",
          "o070080050082",
          "o070080050091",
          "o070080050101",
          "o070080050102",
          "o070080050103",
          "o070080050111",
          "o070080050121",
          "o070080050131",
          "o070080050141",
          "o070080050142",
          "o070080050151",
          "o070080050161",
          "o070080050171",
          "o070080050181",
          "o070080050182",
          "o070080050191",
          "o070080050201"
        ]
      },
      {
        "quote_type": "Normal",
        "words": [
          "o070080070031",
          "o070080070032",
          "o070080070041",
          "o070080070042",
          "o070080070051",
          "o070080070061",
          "o070080070071",
          "o070080070081",
          "o070080070082",
          "o070080070091",
          "o070080070101",
          "o070080070102",
          "o070080070103",
          "o070080070111",
          "o070080070112",
          "o070080070121",
          "o070080070131",
          "o070080070132",
          "o070080070141",
          "o070080070151",
          "o070080070161",
          "o070080070162",
          "o070080070171",
          "o070080070172",
          "o070080070181",
          "o070080070182"
        ]
      },
      {
        "quote_type": "Normal",
        "words": [
          "o070080090061",
          "o070080090062",
          "o070080090063",
          "o070080090071",
          "o070080090072",
          "o070080090081",
          "o070080090091",
          "o070080090101",
          "o070080090102",
          "o070080090111",
          "o070080090112"
        ]
      },
      {
        "quote_type": "Normal",
        "words": [
          "o070080150061",
          "o070080150071",
          "o070080150081",
          "o070080150082",
          "o070080150091",
          "o070080150101",
          "o070080150111",
          "o070080150112",
          "o070080150121",
          "o070080150122",
          "o070080150131",
          "o070080150132",
          "o070080150141",
          "o070080150151",
          "o070080150152",
          "o070080150161",
          "o070080150171",
          "o070080150172",
          "o070080150173",
          "o070080150181",
          "o070080150191",
          "o070080150201",
          "o070080150202",
          "o070080150203",
          "o070080150211",
          "o070080150212",
          "o070080150221"
        ]
      },
      {
        "quote_type": "Normal",
        "words": [
          "o070080180061",
          "o070080180071",
          "o070080180072",
          "o070080180081",
          "o070080180091",
          "o070080180101",
          "o070080180102"
        ]
      },
      {
        "quote_type": "Normal",
        "words": [
          "o070080190021",
          "o070080190022",
          "o070080190031",
          "o070080190041",
          "o070080190042",
          "o070080190051",
          "o070080190061",
          "o070080190071",
          "o070080190081",
          "o070080190091",
          "o070080190101",
          "o070080190102",
          "o070080190111",
          "o070080190121",
          "o070080190131",
          "o070080190132"
        ]
      },
      {
        "quote_type": "Normal",
        "words": [
          "o070080200041",
          "o070080200051",
          "o070080200061",
          "o070080200062"
        ]
      },
      {
        "quote_type": "Normal",
        "words": [
          "o070080230041",
          "o070080230051",
          "o070080230061",
          "o070080230071",
          "o070080230072",
          "o070080230081",
          "o070080230082",
          "o070080230091",
          "o070080230101",
          "o070080230102",
          "o070080230111",
          "o070080230112",
          "o070080230121",
          "o070080230131",
          "o070080230141",
          "o070080230142"
        ]
      },
      {
        "quote_type": "Normal",
        "words": [
          "o070080240041",
          "o070080240051",
          "o070080240052",
          "o070080240061",
          "o070080240071",
          "o070080240072",
          "o070080240081",
          "o070080240082",
          "o070080240091",
          "o070080240101",
          "o070080240111",
          "o070080240112"
        ]
      }
    ]
  }
}