{
  "id": "person:Hermogenes",
  "primary_id": "person:Hermogenes",
  "alternate_sources": {
    "aquifer": [
      "5818|Hermogenes|TyndaleBibleDictionary"
    ],
    "ubsdgnt": [
      "93.125"
    ],
    "tipnr": [
      "Hermogenes@2Ti.1.15"
    ],
    "vizbible": [
      "recoXTE4vaU4eF85p"
    ]
  },
  "type": "person",
  "gender": "male",
  "ubsdgnt": [
    "93.125"
  ],
  "localizations": {
    "eng": {
      "preferred_label": "Hermogenes",
      "descriptions": [
        {
          "source": "acai",
          "gloss": "Hermogenes",
          "article": "person:Hermogenes",
          "description": "Hermogenes, a Christian from Asia Minor mentioned in 2 Timothy 1:15, lived during the New Testament times."
        }
      ]
    },
    "fra": {
      "preferred_label": "Hermogène"
    },
    "spa": {
      "preferred_label": "Hermógenes"
    },
    "arb": {
      "preferred_label": "وَهَرْمُوجَانِسُ"
    },
    "cmn": {
      "preferred_label": "黑摩其尼"
    },
    "hin": {
      "preferred_label": "हिरमुगिनेस"
    },
    "ind": {
      "preferred_label": "Hermogenes"
    },
    "por": {
      "preferred_label": "Hermogenes"
    },
    "rus": {
      "preferred_label": "Ермоген"
    },
    "swh": {
      "preferred_label": "Hermogene"
    },
    "tpi": {
      "preferred_label": "Hermogenes"
    }
  },
  "only_mentioned_in_apocrypha": false,
  "non_biblical": false,
  "lemmas": {
    "el": [
      "Ἑρμογένης"
    ]
  },
  "key_references": [
    "55001015"
  ],
  "references": [
    "55001015"
  ],
  "explicit_instances": {
    "SBLGNT": [
      [
        "n55001015015"
      ]
    ]
  }
}