{
  "id": "person:Jehiel.4",
  "primary_id": "person:Jehiel.4",
  "alternate_sources": {
    "aquifer": [
      "6269|Jehiel|TyndaleBibleDictionary"
    ],
    "ubsdbh": [
      "002902001004000"
    ],
    "tipnr": [
      "Jehiel@2Ch.21.2"
    ],
    "vizbible": [
      "reczy1Y7fPcD5BDQh"
    ]
  },
  "type": "person",
  "gender": "male",
  "father": "person:Jehoshaphat.3",
  "siblings": [
    "person:Jehoram",
    "person:Azariah.12",
    "person:Zechariah.11",
    "person:Azariahu",
    "person:Michael.9",
    "person:Shephatiah.5"
  ],
  "tribe": "group:Judah",
  "related_places": {
    "birth_place": [
      "place:Jerusalem"
    ],
    "death_place": [
      "place:Jerusalem"
    ]
  },
  "ubsdbh": [
    "002902001004000"
  ],
  "localizations": {
    "eng": {
      "preferred_label": "Jehiel (2 Chronicles 21:2)",
      "descriptions": [
        {
          "source": "acai",
          "gloss": "Jehiel (2 Chronicles 21:2)",
          "article": "person:Jehiel.4",
          "description": "A man from the tribe of Judah, son of King Jehoshaphat, and brother to Jehoram, Azariah, Zechariah, Azariahu, Michael, and Shephatiah, mentioned in 2 Chronicles 21:2."
        }
      ]
    }
  },
  "only_mentioned_in_apocrypha": false,
  "non_biblical": false,
  "lemmas": {
    "he": [
      "יְחִיאֵל"
    ]
  },
  "key_references": [
    "14021002"
  ],
  "references": [
    "14021002"
  ],
  "explicit_instances": {
    "wlc": [
      [
        "o140210020062"
      ]
    ]
  }
}