{
  "id": "person:Tryphosa",
  "primary_id": "person:Tryphosa",
  "alternate_sources": {
    "aquifer": [
      "8937|Tryphosa|TyndaleBibleDictionary"
    ],
    "ubsdgnt": [
      "93.367"
    ],
    "tipnr": [
      "Tryphosa@Rom.16.12"
    ],
    "vizbible": [
      "recWEFwHpSwuh93Ag"
    ]
  },
  "type": "person",
  "gender": "female",
  "ubsdgnt": [
    "93.367"
  ],
  "localizations": {
    "eng": {
      "preferred_label": "Tryphosa",
      "descriptions": [
        {
          "source": "acai",
          "gloss": "Tryphosa",
          "article": "person:Tryphosa",
          "description": "Tryphosa was a woman living during the New Testament period and is mentioned in Romans 16:12."
        }
      ]
    },
    "fra": {
      "preferred_label": "Tryphose"
    },
    "spa": {
      "preferred_label": "Trifosa"
    },
    "arb": {
      "preferred_label": "وَتَرِيفُوسَا"
    },
    "cmn": {
      "preferred_label": "土富撒"
    },
    "hau": {
      "preferred_label": "Tiryifosa"
    },
    "hin": {
      "preferred_label": "त्रूफोसा"
    },
    "ind": {
      "preferred_label": "Trifosa"
    },
    "por": {
      "preferred_label": "Trifosa"
    },
    "rus": {
      "preferred_label": "Трифосу"
    },
    "swh": {
      "preferred_label": "Trifosa"
    },
    "tpi": {
      "preferred_label": "Trifosa"
    }
  },
  "only_mentioned_in_apocrypha": false,
  "non_biblical": false,
  "lemmas": {
    "el": [
      "Τρυφῶσα"
    ]
  },
  "key_references": [
    "45016012"
  ],
  "references": [
    "45016012"
  ],
  "explicit_instances": {
    "SBLGNT": [
      [
        "n45016012004"
      ]
    ]
  },
  "subject_referents": {
    "SBLGNT": [
      [
        "n45016012006"
      ]
    ]
  }
}