{
  "id": "person:Vaniah",
  "primary_id": "person:Vaniah",
  "alternate_sources": {
    "aquifer": [
      "9004|Vaniah|TyndaleBibleDictionary"
    ],
    "ubsdbh": [
      "001904001001000"
    ],
    "tipnr": [
      "Vaniah@Ezr.10.36"
    ],
    "vizbible": [
      "recdewaMMETpWlrZi"
    ]
  },
  "type": "person",
  "gender": "male",
  "ubsdbh": [
    "001904001001000"
  ],
  "localizations": {
    "eng": {
      "preferred_label": "Vaniah",
      "descriptions": [
        {
          "source": "acai",
          "gloss": "Vaniah",
          "article": "person:Vaniah",
          "description": "Vaniah, a man who lived during the time of exile and return, is mentioned in Ezra 10:36 as one who married a foreign wife."
        }
      ]
    }
  },
  "only_mentioned_in_apocrypha": false,
  "non_biblical": false,
  "lemmas": {
    "he": [
      "וַנְיָה"
    ]
  },
  "key_references": [
    "15010036"
  ],
  "references": [
    "15010036"
  ],
  "explicit_instances": {
    "wlc": [
      [
        "o150100360011"
      ]
    ]
  }
}